sgtnclient/I18N.py
sgtnclient/__init__.py
sgtnclient/sgtn_bykey.py
sgtnclient/sgtn_client.py
sgtnclient/sgtn_debug.py
sgtnclient/sgtn_locale.py
sgtnclient/sgtn_properties.py
sgtnclient/sgtn_py2_base.py
sgtnclient/sgtn_py37_base.py
sgtnclient/sgtn_py3_base.py
sgtnclient/sgtn_py_base.py
sgtnclient/sgtn_util.py
sgtnclient-0.7.0.dist-info/LICENSE
sgtnclient-0.7.0.dist-info/METADATA
sgtnclient-0.7.0.dist-info/WHEEL
sgtnclient-0.7.0.dist-info/top_level.txt
sgtnclient-0.7.0.dist-info/RECORD
