Metadata-Version: 2.1
Name: sgtnclient
Version: 0.7.0
Summary: Singleton Client
Home-page: https://github.com/vmware/singleton/tree/g11n-python-client
Author: Jasper Jin
Author-email: jasperj@vmware.com
License: EPL-2.0
Platform: UNKNOWN
Classifier: Operating System :: OS Independent
License-File: LICENSE
Requires-Dist: PyYAML
